[1,["61i3SbHAtFcJI8toXL4AmO"],0,[["sp.SkeletonData",["_name","_atlasText","textureNames","_skeletonJson","textures"],-1,3]],[[0,0,1,2,3,4,5]],[[0,"LV57","\r\nLV57.png\r\nsize: 2048,628\r\nformat: RGBA8888\r\nfilter: Linear,Linear\r\nrepeat: none\r\nLayer1\r\n  rotate: false\r\n  xy: 1134, 75\r\n  size: 132, 113\r\n  orig: 132, 113\r\n  offset: 0, 0\r\n  index: -1\r\nLayer10\r\n  rotate: false\r\n  xy: 2, 214\r\n  size: 415, 409\r\n  orig: 415, 409\r\n  offset: 0, 0\r\n  index: -1\r\nLayer11\r\n  rotate: true\r\n  xy: 1841, 409\r\n  size: 214, 155\r\n  orig: 214, 155\r\n  offset: 0, 0\r\n  index: -1\r\nLayer12\r\n  rotate: true\r\n  xy: 171, 102\r\n  size: 110, 166\r\n  orig: 110, 166\r\n  offset: 0, 0\r\n  index: -1\r\nLayer13\r\n  rotate: false\r\n  xy: 1998, 565\r\n  size: 44, 58\r\n  orig: 44, 58\r\n  offset: 0, 0\r\n  index: -1\r\nLayer14\r\n  rotate: false\r\n  xy: 1296, 366\r\n  size: 188, 257\r\n  orig: 188, 257\r\n  offset: 0, 0\r\n  index: -1\r\nLayer15\r\n  rotate: false\r\n  xy: 1998, 504\r\n  size: 42, 59\r\n  orig: 42, 59\r\n  offset: 0, 0\r\n  index: -1\r\nLayer16\r\n  rotate: false\r\n  xy: 1455, 177\r\n  size: 241, 169\r\n  orig: 241, 169\r\n  offset: 0, 0\r\n  index: -1\r\nLayer17\r\n  rotate: true\r\n  xy: 2, 52\r\n  size: 160, 167\r\n  orig: 160, 167\r\n  offset: 0, 0\r\n  index: -1\r\nLayer18\r\n  rotate: false\r\n  xy: 1998, 444\r\n  size: 40, 58\r\n  orig: 40, 58\r\n  offset: 0, 0\r\n  index: -1\r\nLayer19\r\n  rotate: true\r\n  xy: 1698, 178\r\n  size: 168, 232\r\n  orig: 168, 232\r\n  offset: 0, 0\r\n  index: -1\r\nLayer2\r\n  rotate: false\r\n  xy: 1841, 49\r\n  size: 204, 131\r\n  orig: 204, 131\r\n  offset: 0, 0\r\n  index: -1\r\nLayer20\r\n  rotate: false\r\n  xy: 1007, 560\r\n  size: 45, 63\r\n  orig: 45, 63\r\n  offset: 0, 0\r\n  index: -1\r\nLayer21\r\n  rotate: false\r\n  xy: 419, 117\r\n  size: 297, 117\r\n  orig: 297, 117\r\n  offset: 0, 0\r\n  index: -1\r\nLayer22\r\n  rotate: false\r\n  xy: 718, 135\r\n  size: 282, 99\r\n  orig: 282, 99\r\n  offset: 0, 0\r\n  index: -1\r\nLayer23\r\n  rotate: true\r\n  xy: 777, 236\r\n  size: 387, 228\r\n  orig: 387, 228\r\n  offset: 0, 0\r\n  index: -1\r\nLayer24\r\n  rotate: true\r\n  xy: 419, 236\r\n  size: 387, 356\r\n  orig: 387, 356\r\n  offset: 0, 0\r\n  index: -1\r\nLayer25\r\n  rotate: false\r\n  xy: 1486, 396\r\n  size: 193, 227\r\n  orig: 193, 227\r\n  offset: 0, 0\r\n  index: -1\r\nLayer26\r\n  rotate: 270\r\n  xy: 1007, 3\r\n  size: 236, 276\r\n  orig: 236, 276\r\n  offset: 0, 0\r\n  index: -1\r\nLayer27\r\n  rotate: false\r\n  xy: 1681, 348\r\n  size: 158, 275\r\n  orig: 158, 275\r\n  offset: 0, 0\r\n  index: -1\r\nLayer28\r\n  rotate: true\r\n  xy: 1932, 198\r\n  size: 94, 93\r\n  orig: 94, 93\r\n  offset: 0, 0\r\n  index: -1\r\nLayer3\r\n  rotate: true\r\n  xy: 339, 54\r\n  size: 122, 269\r\n  orig: 122, 269\r\n  offset: 0, 0\r\n  index: -1\r\nLayer4\r\n  rotate: false\r\n  xy: 1218, 190\r\n  size: 235, 174\r\n  orig: 235, 174\r\n  offset: 0, 0\r\n  index: -1\r\nLayer6\r\n  rotate: false\r\n  xy: 1218, 190\r\n  size: 235, 174\r\n  orig: 235, 174\r\n  offset: 0, 0\r\n  index: -1\r\nLayer5\r\n  rotate: false\r\n  xy: 1007, 190\r\n  size: 287, 434\r\n  orig: 287, 434\r\n  offset: 0, 0\r\n  index: -1\r\nLayer7\r\n  rotate: 270\r\n  xy: 1376, 38\r\n  size: 137, 275\r\n  orig: 137, 275\r\n  offset: 0, 0\r\n  index: -1\r\nLayer8\r\n  rotate: false\r\n  xy: 1268, 104\r\n  size: 137, 84\r\n  orig: 137, 84\r\n  offset: 0, 0\r\n  index: -1\r\nLayer9\r\n  rotate: false\r\n  xy: 1698, 110\r\n  size: 143, 66\r\n  orig: 143, 66\r\n  offset: 0, 0\r\n  index: -1\r\ntoc\r\n  rotate: true\r\n  xy: 1932, 294\r\n  size: 113, 78\r\n  orig: 113, 78\r\n  offset: 0, 0\r\n  index: -1\r\n",["LV57.png"],{"skeleton":{"hash":"xOMZDT71wmUnKBX+KYDPSt9V32o","spine":"3.8.82","x":-164.59,"y":31.56,"width":326.65,"height":551.06,"images":"./images-57/","audio":"C:/Users/maixu/Downloads/drive-download-20210430T071641Z-001"},"bones":[{"name":"root"},{"name":"all","parent":"root","scaleX":0.5,"scaleY":0.5},{"name":"Layer5","parent":"all","length":189.89,"rotation":113.06,"x":-52.35,"y":372.96},{"name":"Layer7","parent":"Layer5","length":182.8,"rotation":-22.21,"x":185.23,"y":-1.85},{"name":"Layer10","parent":"Layer7","length":302.96,"rotation":0.68,"x":179.47,"y":0.95},{"name":"Layer26","parent":"Layer7","length":200,"rotation":124.49,"x":134.88,"y":19.73},{"name":"Layer28","parent":"Layer26","length":184.32,"rotation":78.74,"x":219.33,"y":3.51},{"name":"Layer30","parent":"Layer28","rotation":50.06,"x":180.94,"y":10.61},{"name":"Layer2","parent":"Layer7","length":170,"rotation":-143.45,"x":153.81,"y":-39.92},{"name":"Layer4","parent":"Layer2","length":103.44,"rotation":40.71,"x":184.72,"y":3.5},{"name":"Layer1","parent":"Layer4","length":101.66,"rotation":13.02,"x":97.48,"y":-0.33},{"name":"Layer8","parent":"Layer5","length":157.49,"rotation":148.92,"x":11.75,"y":21.55,"scaleX":1.0957},{"name":"Layer11","parent":"Layer8","length":137.97,"rotation":-36.57,"x":158.76,"y":0.87},{"name":"Layer9","parent":"all","length":107.84,"rotation":-26.08,"x":-209.39,"y":126.17,"color":"ff3f00ff"},{"name":"Layer3","parent":"Layer5","length":137.25,"rotation":-166.19,"x":-24.02,"y":-25.46,"scaleX":1.0762},{"name":"Layer12","parent":"Layer3","length":156.6,"rotation":-26.98,"x":137.36,"y":-0.77},{"name":"Layer14","parent":"all","length":99.39,"rotation":16.03,"x":89.18,"y":95.67,"color":"ff3f00ff"},{"name":"Layer6","parent":"Layer7","length":328.14,"rotation":-104.93,"x":75.76,"y":96.68},{"name":"Layer23","parent":"Layer6","x":325.99,"y":-1.85},{"name":"Layer22","parent":"Layer10","x":125.2,"y":-98.24},{"name":"Layer13","parent":"Layer10","x":152.89,"y":-71.23},{"name":"Layer27","parent":"Layer30","length":211.63,"rotation":1.45,"x":3.73,"y":-7.15},{"name":"Layer15","parent":"Layer10","length":71.19,"rotation":7.13,"x":281.41,"y":0.78}],"slots":[{"name":"Layer1","bone":"Layer1","attachment":"Layer1"},{"name":"Layer2","bone":"Layer4","attachment":"Layer2"},{"name":"Layer3","bone":"Layer12","attachment":"Layer3"},{"name":"Layer4","bone":"Layer6","attachment":"Layer4"},{"name":"Layer5","bone":"Layer7","attachment":"Layer5"},{"name":"Layer6","bone":"Layer6","attachment":"Layer6"},{"name":"Layer7","bone":"Layer11","attachment":"Layer7"},{"name":"Layer8","bone":"Layer9","attachment":"Layer8"},{"name":"Layer9","bone":"Layer14","attachment":"Layer9"},{"name":"Layer10","bone":"Layer10","attachment":"Layer10"},{"name":"Layer11","bone":"Layer22","attachment":"Layer11"},{"name":"Layer12","bone":"Layer22","attachment":"Layer12"},{"name":"Layer13","bone":"Layer22","attachment":"Layer13"},{"name":"Layer14","bone":"Layer22","attachment":"Layer14"},{"name":"Layer15","bone":"Layer22","attachment":"Layer15"},{"name":"Layer16","bone":"Layer13"},{"name":"Layer17","bone":"Layer13"},{"name":"Layer18","bone":"Layer13"},{"name":"Layer19","bone":"Layer13"},{"name":"Layer20","bone":"Layer13"},{"name":"Layer21","bone":"Layer13"},{"name":"Layer22","bone":"Layer22","attachment":"Layer22"},{"name":"Layer23","bone":"Layer23","attachment":"Layer23"},{"name":"Layer24","bone":"Layer23"},{"name":"Layer25","bone":"Layer23"},{"name":"Layer26","bone":"Layer28","attachment":"Layer26"},{"name":"Layer27","bone":"Layer27","attachment":"Layer27"},{"name":"Layer28","bone":"Layer30","attachment":"Layer28"},{"name":"toc","bone":"Layer15","attachment":"toc"}],"ik":[{"name":"Layer9","order":1,"target":"Layer9","bendPositive":false,"bones":["Layer8","Layer11"]},{"name":"Layer14","target":"Layer14","bendPositive":false,"bones":["Layer3","Layer12"]}],"skins":[{"name":"default","attachments":{"Layer1":{"Layer1":{"x":57.13,"y":-1.16,"rotation":24.29,"width":132,"height":113}},"Layer10":{"Layer10":{"x":146.63,"y":-22.94,"rotation":-91.53,"width":415,"height":409}},"Layer11":{"Layer11":{"type":"mesh","hull":4,"width":214,"height":155,"uvs":[1,1,0,1,0,0,1,0],"triangles":[1,2,3,1,3,0],"vertices":[-171.51,-80.85,-165.81,133.07,-10.87,128.95,-16.57,-84.98],"edges":[0,2,2,4,4,6,0,6]}},"Layer12":{"Layer12":{"type":"mesh","hull":4,"width":110,"height":166,"uvs":[1,1,0,1,0,0,1,0],"triangles":[1,2,3,1,3,0],"vertices":[-8.86,-96.19,-5.93,13.77,160.01,9.36,157.08,-100.6],"edges":[0,2,2,4,4,6,0,6]}},"Layer13":{"Layer13":{"type":"mesh","hull":4,"width":44,"height":58,"uvs":[1,1,0,1,0,0,1,0],"triangles":[1,2,3,1,3,0],"vertices":[7.69,-75.62,8.86,-31.64,66.84,-33.18,65.67,-77.16],"edges":[0,2,2,4,4,6,0,6]}},"Layer14":{"Layer14":{"type":"mesh","hull":4,"width":188,"height":257,"uvs":[1,1,0,1,0,0,1,0],"triangles":[1,2,3,1,3,0],"vertices":[-81.07,9.77,-76.06,197.71,180.85,190.87,175.84,2.93],"edges":[0,2,2,4,4,6,0,6]}},"Layer15":{"Layer15":{"type":"mesh","hull":4,"width":42,"height":59,"uvs":[1,1,0,1,0,0,1,0],"triangles":[1,2,3,1,3,0],"vertices":[-9.24,39.87,-8.12,81.86,50.86,80.29,49.74,38.3],"edges":[0,2,2,4,4,6,0,6]}},"Layer16":{"Layer16":{"type":"mesh","hull":4,"width":241,"height":169,"uvs":[1,1,0,1,0,0,1,0],"triangles":[1,2,3,1,3,0],"vertices":[-220.43,-81.93,-214.02,158.99,-45.08,154.49,-51.49,-86.43],"edges":[0,2,2,4,4,6,0,6]}},"Layer17":{"Layer17":{"type":"mesh","hull":4,"width":160,"height":167,"uvs":[1,1,0,1,0,0,1,0],"triangles":[1,2,3,1,3,0],"vertices":[-31.16,-111.98,-26.9,47.97,140.04,43.52,135.78,-116.42],"edges":[0,2,2,4,4,6,0,6]}},"Layer18":{"Layer18":{"type":"mesh","hull":4,"width":40,"height":58,"uvs":[1,1,0,1,0,0,1,0],"triangles":[1,2,3,1,3,0],"vertices":[-14.4,-83.41,-13.33,-43.43,44.65,-44.97,43.58,-84.96],"edges":[0,2,2,4,4,6,0,6]}},"Layer19":{"Layer19":{"type":"mesh","hull":4,"width":168,"height":232,"uvs":[1,1,0,1,0,0,1,0],"triangles":[1,2,3,1,3,0],"vertices":[-98.13,2.85,-93.66,170.79,138.26,164.61,133.79,-3.33],"edges":[0,2,2,4,4,6,0,6]}},"Layer2":{"Layer2":{"type":"mesh","hull":26,"width":204,"height":131,"uvs":[0.06994,0,0.10891,0.14992,0.16087,0.34614,0.23232,0.53225,0.30506,0.68396,0.40509,0.7932,0.49278,0.84851,0.61229,0.87278,0.73439,0.83233,0.8578,0.75343,0.96432,0.65633,1,0.73118,0.98251,0.8303,0.89287,0.89706,0.77596,0.96179,0.65905,1,0.53305,1,0.44341,0.97393,0.34469,0.90313,0.26675,0.80603,0.18361,0.67252,0.11736,0.51675,0.0654,0.36099,0.02513,0.21534,0,0.09194,0,0],"triangles":[16,7,15,15,8,14,15,7,8,16,6,7,13,14,9,14,8,9,13,9,12,9,10,12,12,10,11,17,6,16,18,5,17,17,5,6,18,19,5,19,4,5,19,20,4,20,3,4,20,21,3,21,2,3,21,22,2,2,22,1,22,23,1,23,24,1,24,0,1,24,25,0],"vertices":[2,8,8.28,26.04,0.99903,9,-33.1,141.79,0.00097,2,8,45.99,12.34,0.99281,9,-21.89,103.47,0.00719,2,8,85.84,0.65,0.97003,9,-10.35,64.17,0.02997,2,8,111.7,-2.78,0.91309,9,-3.47,38.54,0.08691,2,8,132.06,-3.45,0.80571,9,2.97,18.47,0.19429,2,8,149.27,3.49,0.64733,9,14.34,3.82,0.35267,2,8,158.13,12.62,0.45994,9,23.85,-2.67,0.54006,2,8,168.06,29.41,0.28107,9,40.88,-6.85,0.71893,2,8,173.27,51.91,0.14315,9,61.69,-3.87,0.85685,2,8,176.84,77.88,0.0585,9,85.67,2.67,0.9415,2,8,178.27,102.72,0.01838,9,108.33,11.22,0.98162,2,8,190.02,102.51,0.00719,9,112.87,0.31,0.99281,2,8,198.57,91.83,0.01702,9,106.84,-11.79,0.98298,2,8,195.99,72.13,0.05486,9,88.35,-17.18,0.94514,2,8,191.6,48.32,0.13615,9,65.96,-22.12,0.86385,2,8,186.66,26.83,0.27052,9,46.12,-24.96,0.72948,2,8,178.36,7.05,0.44717,9,27.02,-23.54,0.55283,2,8,172.31,-4.72,0.63485,9,16.29,-20.69,0.36515,2,8,159.37,-14.5,0.79584,9,4.14,-11.08,0.20416,2,8,144.21,-19,0.90686,9,-4.79,2.16,0.09314,2,8,122.5,-21.64,0.96695,9,-15.42,21.53,0.03305,2,8,99.1,-19.9,0.99168,9,-23.23,43.82,0.00832,2,8,76.75,-15.9,0.99875,9,-28.8,65.9,0.00125,2,8,40.97,-5.08,0.99996,9,-40.67,100.89,0.00004,1,8,9.23,7.39,1,1,8,-0.34,14.71,1],"edges":[0,2,2,4,4,6,6,8,8,10,10,12,12,14,14,16,16,18,18,20,20,22,22,24,24,26,26,28,28,30,30,32,32,34,34,36,36,38,38,40,40,42,42,44,44,46,46,48,48,50,0,50]}},"Layer20":{"Layer20":{"type":"mesh","hull":4,"width":45,"height":63,"uvs":[1,1,0,1,0,0,1,0],"triangles":[1,2,3,1,3,0],"vertices":[-38.35,31.27,-37.16,76.25,25.82,74.57,24.62,29.59],"edges":[0,2,2,4,4,6,0,6]}},"Layer21":{"Layer21":{"type":"mesh","hull":4,"width":297,"height":117,"uvs":[1,1,0,1,0,0,1,0],"triangles":[1,2,3,1,3,0],"vertices":[-125.77,-133.46,-117.86,163.43,-0.9,160.32,-8.81,-136.58],"edges":[0,2,2,4,4,6,0,6]}},"Layer22":{"Layer22":{"type":"mesh","hull":4,"width":282,"height":99,"uvs":[1,1,0,1,0,0,1,0],"triangles":[1,2,3,1,3,0],"vertices":[132.28,-55.31,139.79,226.59,238.76,223.95,231.25,-57.95],"edges":[0,2,2,4,4,6,0,6]}},"Layer23":{"Layer23":{"x":50.89,"y":-55.45,"rotation":14.09,"width":387,"height":228},"Layer24":{"x":35.31,"y":6.63,"rotation":14.09,"width":387,"height":356}},"Layer25":{"Layer25":{"type":"mesh","hull":4,"width":193,"height":227,"uvs":[1,1,0,1,0,0,1,0],"triangles":[1,2,3,1,3,0],"vertices":[105,-71.77,-82.2,-118.75,-137.46,101.42,49.73,148.4],"edges":[0,2,2,4,4,6,0,6]}},"Layer26":{"Layer26":{"type":"mesh","hull":25,"width":236,"height":276,"uvs":[1,0.94477,0.88274,0.92923,0.74062,0.89532,0.61172,0.84162,0.50926,0.76956,0.40846,0.68196,0.31426,0.56609,0.24155,0.4488,0.17875,0.31739,0.12918,0.19446,0.08786,0.08141,0.05812,0,0.0135,0,0,0.01359,0.0135,0.09696,0.05481,0.22978,0.10439,0.34565,0.16719,0.47706,0.2432,0.60989,0.34235,0.73283,0.45142,0.83315,0.5671,0.91087,0.71583,0.96598,0.86952,0.99989,1,1],"triangles":[11,13,12,10,14,13,10,13,11,9,15,14,9,14,10,15,9,8,16,15,8,16,8,7,17,16,7,6,17,7,18,17,6,18,6,5,19,18,5,4,19,5,20,19,4,20,4,3,21,20,3,2,21,3,22,21,2,1,22,2,23,22,1,1,0,24,23,1,24],"vertices":[2,5,-26.36,4.08,0.94305,6,-126.08,-86.53,0.05695,2,5,12.02,1.59,0.92041,6,-121.56,-77.38,0.07959,2,5,51.63,7.23,0.86972,6,-102,-56.66,0.13028,2,5,93.11,8.97,0.79081,6,-75.94,-42.22,0.20919,2,5,146.06,8.06,0.68656,6,-40.07,-48.54,0.31344,2,5,180.77,0.31,0.56435,6,-7.22,-37.77,0.43565,2,5,210.28,-16.25,0.43558,6,29.41,-24.05,0.56442,2,5,235.92,-35.7,0.31317,6,64.49,-15.43,0.68683,2,5,262.33,-59.66,0.20826,6,102.46,-11.27,0.79174,2,5,285.97,-83.13,0.12756,6,137.33,-10.14,0.87244,2,5,307.73,-105.17,0.07276,6,169.23,-10.9,0.92724,2,5,323.8,-121.02,0.04196,6,192.3,-11.83,0.95804,2,5,332.42,-115.69,0.03222,6,196.3,-1.7,0.96778,2,5,333.7,-110.81,0.04191,6,194.2,2.27,0.95809,2,5,320.61,-92.55,0.07169,6,172.11,6.98,0.92831,2,5,295.94,-65.81,0.12377,6,135.15,9.99,0.87623,2,5,273.08,-44.04,0.19984,6,102.02,8.31,0.80016,2,5,244.57,-20.2,0.25878,6,63.53,6.19,0.74122,2,5,212.5,2.34,0.30312,6,23.29,1.99,0.69688,2,5,194.34,20.76,0.72335,6,-12.22,-24.99,0.27665,2,5,146.81,34.22,0.7239,6,-47.29,-26.29,0.2761,2,5,96.8,39.4,0.76594,6,-80.13,-27.66,0.23406,2,5,49.89,32.67,0.84978,6,-111.49,-45.65,0.15022,2,5,6.31,25.71,0.90763,6,-132.36,-67.28,0.09237,2,5,-34.32,17.19,0.93867,6,-140.17,-80.39,0.06133],"edges":[0,2,2,4,4,6,6,8,8,10,10,12,12,14,14,16,16,18,18,20,20,22,22,24,24,26,26,28,28,30,30,32,32,34,34,36,36,38,38,40,40,42,42,44,44,46,46,48,0,48]}},"Layer27":{"Layer27":{"x":71.16,"y":-5.96,"rotation":-114.41,"width":158,"height":275}},"Layer28":{"Layer28":{"x":6.23,"y":-20,"rotation":-112.95,"width":94,"height":93}},"Layer3":{"Layer3":{"type":"mesh","hull":27,"width":122,"height":269,"uvs":[0.10223,0,0,0,0,0.0456,0.12665,0.08936,0.28787,0.15804,0.41955,0.23286,0.51178,0.30354,0.60589,0.38899,0.68222,0.47698,0.74087,0.57616,0.78381,0.67352,0.82038,0.76944,0.84631,0.87016,0.86062,0.94805,0.88129,1,1,1,1,0.94589,0.99737,0.86367,0.9767,0.7627,0.94331,0.66823,0.88288,0.55814,0.81928,0.46006,0.74613,0.36305,0.64436,0.27218,0.53782,0.19501,0.41219,0.12361,0.23251,0.04572],"triangles":[14,16,15,14,13,16,13,12,16,12,17,16,17,12,18,12,11,18,11,19,18,11,10,19,19,10,20,10,9,20,9,21,20,9,8,21,21,8,22,8,7,22,22,7,23,7,6,23,6,5,23,5,24,23,4,25,5,5,25,24,3,26,4,4,26,25,2,0,3,3,0,26,2,1,0],"vertices":[2,14,-3.76,10.47,0.99906,15,-130.86,-54.01,0.00094,2,14,-11.25,0.49,1,15,-133,-66.3,0,2,14,-1.43,-6.87,0.99863,15,-120.92,-68.4,0.00137,2,14,17.25,-1.57,0.99039,15,-106.67,-55.2,0.00961,2,14,43.84,3.08,0.96157,15,-85.09,-39,0.03843,2,14,69.58,3.85,0.89296,15,-62.5,-26.63,0.10704,2,14,91.54,1.45,0.76948,15,-41.84,-18.81,0.23052,2,14,116.82,-3.16,0.59664,15,-17.22,-11.45,0.40336,2,14,141.34,-9.91,0.40323,15,7.69,-6.34,0.59677,2,14,166.98,-20.2,0.23041,15,35.21,-3.88,0.76959,2,14,191.07,-31.72,0.10697,15,61.91,-3.22,0.89303,2,14,214.39,-43.63,0.0384,15,88.09,-3.25,0.9616,2,14,237.96,-57.36,0.0096,15,115.33,-4.79,0.9904,2,14,255.77,-68.53,0.00137,15,136.27,-6.67,0.99863,1,15,150.47,-6.59,1,2,14,277.15,-63.31,0.00043,15,152.96,7.68,0.99957,2,14,265.51,-54.58,0.00398,15,138.62,10.18,0.99602,2,14,247.62,-41.57,0.01874,15,116.77,13.66,0.98127,2,14,224.38,-27.29,0.06015,15,89.58,15.85,0.93985,2,14,201.61,-15.3,0.14614,15,63.85,16.2,0.85386,2,14,173.49,-3.43,0.28525,15,33.41,14.02,0.71475,2,14,147.73,6.2,0.46461,15,6.08,10.91,0.53539,2,14,121.5,14.71,0.6515,15,-21.16,6.6,0.3485,2,14,94.49,19.45,0.80869,15,-47.37,-1.43,0.19131,2,14,70.09,21.5,0.91475,15,-70.05,-10.67,0.08525,2,14,45.53,20.77,0.97072,15,-91.61,-22.47,0.02928,2,14,15.61,15.8,0.99301,15,-116.01,-40.46,0.00699],"edges":[0,2,2,4,4,6,6,8,8,10,10,12,12,14,14,16,16,18,18,20,20,22,22,24,24,26,26,28,28,30,30,32,32,34,34,36,36,38,38,40,40,42,42,44,44,46,46,48,48,50,50,52,0,52]}},"Layer4":{"Layer4":{"x":208.23,"y":39.56,"rotation":14.09,"width":235,"height":174}},"Layer5":{"Layer5":{"type":"mesh","hull":30,"width":287,"height":434,"uvs":[0.56051,0.99905,0.71736,0.99542,0.83536,0.96972,0.93177,0.92309,0.99077,0.84601,1,0.75085,0.97207,0.65283,0.91307,0.56624,0.7993,0.49659,0.7475,0.46899,0.73311,0.42236,0.7216,0.33006,0.70433,0.24632,0.67842,0.15306,0.63525,0.08264,0.54316,0.02174,0.43235,0,0.3345,0,0.2424,0.0322,0.16613,0.08644,0.10138,0.17494,0.05533,0.27106,0.01791,0.37098,0,0.47661,0,0.58794,0.02079,0.66886,0.08843,0.76402,0.17908,0.84776,0.31867,0.93246,0.44099,0.97814,0.38709,0.07802,0.39125,0.17156,0.39957,0.2651,0.39957,0.36414,0.41413,0.4508,0.43493,0.52233,0.48694,0.61862,0.55142,0.72454,0.63463,0.81945,0.72615,0.92812],"triangles":[34,22,33,22,21,33,35,10,9,35,34,10,33,21,32,32,21,20,34,33,10,33,11,10,20,19,31,19,30,31,11,32,12,20,31,32,11,33,32,19,18,30,32,13,12,32,31,13,31,14,13,14,30,15,15,30,16,30,14,31,18,17,30,30,17,16,1,0,39,1,39,2,38,39,0,0,29,38,29,28,38,2,39,3,28,37,38,28,27,37,3,39,4,4,39,38,37,27,36,4,38,5,5,38,6,27,26,36,26,25,36,38,37,6,37,7,6,37,8,7,8,36,9,8,37,36,35,25,24,25,35,36,35,24,34,23,22,34,36,35,9,34,24,23],"vertices":[2,2,-19.74,21.97,0.99922,3,-198.76,-55.44,0.00078,2,2,-52.41,3.84,0.99701,3,-222.15,-84.57,0.00299,2,2,-53.38,-28.99,0.99062,3,-210.63,-115.34,0.00938,2,2,-38.88,-40.34,0.97518,3,-192.92,-120.37,0.02482,2,2,-11.45,-50.87,0.94319,3,-163.55,-119.73,0.05681,2,2,16.65,-44.37,0.88586,3,-139.99,-103.1,0.11414,2,2,50.83,-35.09,0.79632,3,-111.86,-81.58,0.20368,2,2,80.54,-32,0.67425,3,-85.52,-67.49,0.32575,2,2,121.71,-29.15,0.52877,3,-48.48,-49.29,0.47123,2,2,165.56,-36.1,0.37758,3,-5.26,-39.15,0.62242,2,2,195.56,-38.16,0.24107,3,23.3,-29.71,0.75893,2,2,229.32,-50.71,0.13487,3,59.29,-28.57,0.86513,2,2,269,-64.89,0.0645,3,101.39,-26.69,0.9355,2,2,301.98,-82.4,0.02556,3,138.54,-30.43,0.97444,2,2,331.24,-100.06,0.00833,3,172.3,-35.72,0.99167,2,2,355.99,-115.65,0.00386,3,201.12,-40.79,0.99614,2,2,377.13,-90.08,0.00851,3,211.02,-9.14,0.99149,2,2,368.94,-80.08,0.02594,3,199.65,-2.97,0.97406,2,2,360.14,-67.17,0.06634,3,186.62,5.66,0.93367,2,2,348.38,-53.48,0.14202,3,170.56,13.88,0.85798,2,2,326.59,-40.01,0.2598,3,145.3,18.11,0.7402,2,2,303.62,-22.99,0.41345,3,117.59,25.19,0.58655,2,2,279.66,-8.23,0.58214,3,89.84,29.79,0.41786,2,2,255.84,4.83,0.73801,3,62.85,32.88,0.26199,2,2,218.27,19.04,0.85866,3,22.69,31.83,0.14134,2,2,180.93,29.34,0.93612,3,-15.77,27.25,0.06388,2,2,136.81,33.24,0.97666,3,-58.09,14.19,0.02334,2,2,93.79,37.5,0.99347,3,-99.53,1.86,0.00653,2,2,55.83,35.9,0.99871,3,-134.07,-13.97,0.00129,2,2,19.5,28.33,0.99971,3,-164.83,-34.72,0.00029,2,2,351.06,-64.87,0.01612,3,177.35,4.35,0.98388,2,2,313.24,-50.07,0.03865,3,136.74,3.75,0.96135,2,2,274.95,-36.37,0.10361,3,96.12,1.96,0.89639,2,2,235.4,-19.54,0.22261,3,53.14,2.6,0.77739,2,2,199.16,-8.65,0.39107,3,15.47,-1.03,0.60893,2,2,168.26,-1.99,0.5822,3,-15.66,-6.54,0.4178,2,2,123.96,0.65,0.7561,3,-57.67,-20.85,0.2439,2,2,74.41,1.62,0.88309,3,-103.9,-38.68,0.11691,2,2,27.16,-4.22,0.95489,3,-145.44,-61.95,0.04511,2,2,-26.52,-9.92,0.98051,3,-192.99,-87.52,0.01949],"edges":[0,2,2,4,4,6,6,8,8,10,10,12,12,14,14,16,16,18,18,20,20,22,22,24,24,26,26,28,28,30,30,32,32,34,34,36,36,38,38,40,40,42,42,44,44,46,46,48,48,50,50,52,52,54,54,56,56,58,0,58,60,62,62,64,64,66,66,68,68,70,70,72,72,74,74,76,76,78]}},"Layer6":{"Layer6":{"x":92.81,"y":6.47,"rotation":14.09,"width":235,"height":174}},"Layer7":{"Layer7":{"type":"mesh","hull":23,"width":137,"height":275,"uvs":[0.83981,0,0.85178,0.10438,0.85417,0.21173,0.82784,0.32265,0.79192,0.43358,0.7327,0.54935,0.62736,0.6567,0.47652,0.76285,0.30415,0.84753,0.14134,0.90717,0,0.94772,0,1,0.08388,1,0.23711,0.96681,0.41667,0.91313,0.6082,0.82487,0.75664,0.72945,0.8979,0.5911,0.96014,0.46586,1,0.33466,1,0.21062,1,0.10566,1,0],"triangles":[9,13,12,9,12,10,10,12,11,13,8,14,13,9,8,15,8,7,15,14,8,15,7,16,7,6,16,16,6,17,6,5,17,17,5,18,5,4,18,18,4,19,19,4,3,19,3,20,3,2,20,20,2,21,2,1,21,1,22,21,1,0,22],"vertices":[1,11,-7.92,-13.77,1,2,11,20.28,-8.14,0.99589,12,-105.84,-89.75,0.00411,2,11,49.47,-3.69,0.97532,12,-85.05,-68.79,0.02468,2,11,80.17,-3.01,0.9136,12,-60.8,-49.94,0.0864,2,11,111.07,-3.62,0.79017,12,-35.62,-32.02,0.20983,2,11,143.73,-7.21,0.60501,12,-7.25,-15.45,0.39499,2,11,174.97,-17.38,0.39514,12,23.9,-5,0.60486,2,11,206.76,-33.77,0.20995,12,59.19,0.78,0.79005,2,11,233.12,-53.9,0.08647,12,92.36,0.32,0.91353,2,11,252.47,-73.7,0.02472,12,119.7,-4.05,0.97528,2,11,266.22,-91.32,0.00412,12,141.23,-10.01,0.99588,2,11,280.45,-89.31,0,12,151.47,0.09,1,2,11,278.85,-77.93,0.00254,12,143.4,8.27,0.99746,2,11,266.88,-58.42,0.01682,12,122.16,16.81,0.98318,2,11,248.83,-36.12,0.06281,12,94.38,23.96,0.93719,2,11,221.13,-13.53,0.16267,12,58.67,25.6,0.83733,2,11,192.31,2.95,0.32424,12,25.71,21.66,0.67576,2,11,151.93,16.8,0.52468,12,-14.97,8.73,0.47532,2,11,116.64,20.44,0.71931,12,-45.48,-9.38,0.28069,2,11,80.15,20.81,0.86637,12,-75.01,-30.82,0.13363,2,11,46.37,16.05,0.9517,12,-99.3,-54.78,0.0483,2,11,17.79,12.02,0.98802,12,-119.85,-75.04,0.01198,2,11,-10.98,7.96,0.99843,12,-140.54,-95.44,0.00157],"edges":[0,2,2,4,4,6,6,8,8,10,10,12,12,14,14,16,16,18,18,20,20,22,22,24,24,26,26,28,28,30,30,32,32,34,34,36,36,38,38,40,40,42,42,44,0,44]}},"Layer8":{"Layer8":{"x":55.98,"y":3.96,"rotation":26.08,"width":137,"height":84}},"Layer9":{"Layer9":{"x":46.43,"y":0.66,"rotation":-16.03,"width":143,"height":66}},"toc":{"toc":{"x":77.16,"y":29.03,"scaleX":1.8102,"scaleY":1.8102,"rotation":-87.87,"width":113,"height":78}}}}],"animations":{"finish":{"slots":{"Layer11":{"attachment":[{"name":null},{"time":0.1667,"name":"Layer11"}]},"Layer12":{"attachment":[{"name":null},{"time":0.1667,"name":"Layer12"}]},"Layer13":{"attachment":[{"name":null},{"time":0.1667,"name":"Layer13"}]},"Layer14":{"attachment":[{"name":null},{"time":0.1667,"name":"Layer14"}]},"Layer15":{"attachment":[{"name":null},{"time":0.1667,"name":"Layer15"}]},"Layer16":{"attachment":[{"name":"Layer16"},{"time":0.1667,"name":null}]},"Layer17":{"attachment":[{"name":"Layer17"},{"time":0.1667,"name":null}]},"Layer18":{"attachment":[{"name":"Layer18"},{"time":0.1667,"name":null}]},"Layer19":{"attachment":[{"name":"Layer19"},{"time":0.1667,"name":null}]},"Layer20":{"attachment":[{"name":"Layer20"},{"time":0.1667,"name":null}]},"Layer21":{"attachment":[{"time":0.1667,"name":"Layer21"}]},"Layer22":{"attachment":[{"name":null},{"time":0.1667,"name":"Layer22"}]},"Layer23":{"attachment":[{"name":"Layer24"}]},"Layer25":{"attachment":[{"time":0.1667,"name":"Layer25"}]}},"bones":{"Layer23":{"rotate":[{"angle":-1.59}]},"Layer10":{"rotate":[{"angle":-0.29,"curve":0.25,"c3":0.75},{"time":0.1667,"angle":2.9,"curve":0.25,"c3":0.75},{"time":0.5,"angle":4.28,"curve":0.25,"c3":0.75},{"time":1.1667,"angle":1.52,"curve":0.25,"c3":0.625,"c4":0.5},{"time":1.5,"angle":2.9}]},"Layer6":{"rotate":[{"angle":-4.35}]},"Layer5":{"rotate":[{"angle":-3.88,"curve":"stepped"},{"time":0.1667,"angle":-3.88,"curve":0.25,"c3":0.75},{"time":0.8333,"angle":-6.63,"curve":0.25,"c3":0.75},{"time":1.5,"angle":-3.88}],"translate":[{"y":20.44,"curve":0.25,"c3":0.75},{"time":0.1667,"y":5.74,"curve":0.25,"c3":0.75},{"time":0.8333,"y":30.81,"curve":0.25,"c3":0.75},{"time":1.5,"y":5.74}]},"Layer4":{"rotate":[{"angle":-6.64,"curve":0.25,"c3":0.75},{"time":0.1667,"angle":-13.53,"curve":0.25,"c3":0.75},{"time":0.6667,"angle":-6.64,"curve":0.25,"c3":0.75},{"time":1.3333,"angle":-15.09,"curve":0.276,"c3":0.621,"c4":0.4},{"time":1.5,"angle":-13.53}]},"Layer7":{"rotate":[{"angle":0.33,"curve":0.25,"c3":0.75},{"time":0.1667,"angle":4.39,"curve":0.25,"c3":0.75},{"time":0.3333,"angle":4.9,"curve":0.25,"c3":0.75},{"time":1,"angle":2.14,"curve":0.242,"c3":0.667,"c4":0.67},{"time":1.5,"angle":4.39}]},"Layer2":{"rotate":[{"angle":-4.07,"curve":0.25,"c3":0.75},{"time":0.1667,"angle":-8.29,"curve":0.25,"c3":0.75},{"time":0.5,"angle":-4.07,"curve":0.25,"c3":0.75},{"time":1.1667,"angle":-12.52,"curve":0.25,"c3":0.625,"c4":0.5},{"time":1.5,"angle":-8.29}]},"Layer26":{"rotate":[{"angle":-27.28,"curve":0.25,"c3":0.75},{"time":0.1667,"angle":37.08,"curve":0.25,"c3":0.75},{"time":0.5,"angle":40.57,"curve":0.25,"c3":0.75},{"time":1.1667,"angle":33.59,"curve":0.25,"c3":0.625,"c4":0.5},{"time":1.5,"angle":37.08}]},"Layer1":{"rotate":[{"angle":-8.14}]},"Layer8":{"rotate":[{"angle":9,"curve":0.25,"c3":0.75},{"time":0.1667,"angle":11.76}],"scale":[{"x":1.127}]},"Layer11":{"rotate":[{"angle":-11.42,"curve":0.25,"c3":0.75},{"time":0.1667,"angle":-20.68}]},"Layer30":{"rotate":[{"angle":-31.37,"curve":0.25,"c3":0.75},{"time":0.1667,"angle":21.2}]},"Layer3":{"rotate":[{"angle":8.54,"curve":0.25,"c3":0.75},{"time":0.1667,"angle":14.53}],"scale":[{"x":1.127}]},"Layer12":{"rotate":[{"angle":-15.54,"curve":0.25,"c3":0.75},{"time":0.1667,"angle":-25.48}]},"Layer28":{"rotate":[{"angle":-29.86,"curve":0.25,"c3":0.75},{"time":0.1667,"angle":-12.03,"curve":0.25,"c3":0.75},{"time":0.6667,"angle":-3.75,"curve":0.25,"c3":0.75},{"time":1.3333,"angle":-13.9,"curve":0.276,"c3":0.621,"c4":0.4},{"time":1.5,"angle":-12.03}]}},"deform":{"default":{"Layer11":{"Layer11":[{"time":0.1667,"curve":0.25,"c3":0.75},{"time":0.8333,"curve":0.25,"c3":0.75,"vertices":[-19.12219,-23.80431,-18.87305,8.50077,8.5083,92.39906]},{"time":1.5}]},"Layer12":{"Layer12":[{"time":0.1667,"curve":0.25,"c3":0.75},{"time":0.8333,"curve":0.25,"c3":0.75,"vertices":[6.34998,-18.22145,0.82343,22.70929,-1.76758,23.37833,0.5387,-14.28259]},{"time":1.5}]},"Layer13":{"Layer13":[{"time":0.1667,"curve":0.25,"c3":0.75},{"time":0.8333,"curve":0.25,"c3":0.75,"vertices":[13.53705,10.56796,11.82239,29.14168,0.53363,9.27614,1.81635,-5.11816]},{"time":1.5}]},"Layer14":{"Layer14":[{"time":0.1667,"curve":0.25,"c3":0.75},{"time":0.8333,"curve":0.25,"c3":0.75,"vertices":[18.14178,-4.03395,-14.10309,22.82441,-60.14496,27.7224,-21.41113,0.81407]},{"time":1.5}]},"Layer15":{"Layer15":[{"time":0.1667,"curve":0.25,"c3":0.75},{"time":0.8333,"curve":0.25,"c3":0.75,"vertices":[4.67529,4.60408,3.39337,18.99834,-10.56415,14.0018,-8.37665,-3.18354]},{"time":1.5}]},"Layer21":{"Layer21":[{"curve":0.25,"c3":0.75},{"time":0.1667,"curve":0.25,"c3":0.75,"vertices":[23.00848,4.00704,22.79907,-3.85785,19.70087,-3.77532,19.91028,4.08955]},{"time":0.8333,"curve":0.25,"c3":0.75,"vertices":[-17.1275,-9.15014,17.51886,11.808,70.02509,39.20583,35.16193,4.05016]},{"time":1.5,"vertices":[23.00848,4.00704,22.79907,-3.85785,19.70087,-3.77532,19.91028,4.08955]}]},"Layer22":{"Layer22":[{"time":0.1667,"curve":0.25,"c3":0.75},{"time":0.8333,"curve":0.25,"c3":0.75,"vertices":[5.01526,30.23369,4.03595,-30.70815,24.50616,-30.46119,25.48529,30.48061]},{"time":1.5}]}}}},"quest1":{"bones":{"Layer5":{"translate":[{"curve":0.25,"c3":0.75},{"time":0.6667,"y":-9.38,"curve":0.25,"c3":0.75},{"time":1.3333}]},"Layer7":{"rotate":[{"angle":-0.36,"curve":0.379,"c2":0.6,"c3":0.724},{"time":0.1667,"curve":0.25,"c3":0.75},{"time":0.8333,"angle":-1.97,"curve":0.242,"c3":0.667,"c4":0.67},{"time":1.3333,"angle":-0.36}]},"Layer10":{"rotate":[{"angle":-0.98,"curve":0.375,"c2":0.5,"c3":0.75},{"time":0.3333,"curve":0.25,"c3":0.75},{"time":1,"angle":-1.97,"curve":0.25,"c3":0.625,"c4":0.5},{"time":1.3333,"angle":-0.98}]},"Layer26":{"rotate":[{"angle":-4.09,"curve":0.375,"c2":0.5,"c3":0.75},{"time":0.3333,"curve":0.25,"c3":0.75},{"time":1,"angle":-8.18,"curve":0.25,"c3":0.625,"c4":0.5},{"time":1.3333,"angle":-4.09}]},"Layer28":{"rotate":[{"angle":-6.67,"curve":0.333,"c2":0.33,"c3":0.758},{"time":0.5,"curve":0.25,"c3":0.75},{"time":1.1667,"angle":-8.18,"curve":0.276,"c3":0.621,"c4":0.4},{"time":1.3333,"angle":-6.67}]},"Layer30":{"rotate":[{"angle":-8.18,"curve":0.25,"c3":0.75},{"time":0.6667,"curve":0.25,"c3":0.75},{"time":1.3333,"angle":-8.18}]},"Layer2":{"rotate":[{"angle":-4.07,"curve":0.375,"c2":0.5,"c3":0.75},{"time":0.3333,"curve":0.25,"c3":0.75},{"time":1,"angle":-8.14,"curve":0.25,"c3":0.625,"c4":0.5},{"time":1.3333,"angle":-4.07}]},"Layer4":{"rotate":[{"angle":-6.64,"curve":0.333,"c2":0.33,"c3":0.758},{"time":0.5,"curve":0.25,"c3":0.75},{"time":1.1667,"angle":-8.14,"curve":0.276,"c3":0.621,"c4":0.4},{"time":1.3333,"angle":-6.64}]},"Layer1":{"rotate":[{"angle":-8.14,"curve":0.25,"c3":0.75},{"time":0.6667,"curve":0.25,"c3":0.75},{"time":1.3333,"angle":-8.14}]},"Layer8":{"rotate":[{"angle":1.42},{"time":1.3333}]},"Layer11":{"rotate":[{"angle":-2.51},{"time":1.3333}]},"Layer3":{"rotate":[{"angle":-0.51},{"time":1.3333}]},"Layer12":{"rotate":[{"angle":0.88},{"time":1.3333}]}},"deform":{"default":{"Layer11":{"Layer11":[{"curve":0.25,"c3":0.75},{"time":0.6667,"curve":0.25,"c3":0.75,"vertices":[24.41467,-7.83796,-34.43042,4.69171,24.72565,39.53609]},{"time":1.3333}]},"Layer12":{"Layer12":[{"curve":0.25,"c3":0.75},{"time":0.6667,"curve":0.25,"c3":0.75,"vertices":[0.27216,-14.79756,-0.24353,13.02165,-15.04169,12.7478,-14.526,-15.07141]},{"time":1.3333}]},"Layer13":{"Layer13":[{"curve":0.25,"c3":0.75},{"time":0.6667,"curve":0.25,"c3":0.75,"vertices":[-2.58905,-5.61351,-3.2699,9.58279,-14.91339,8.46207,-14.23279,-6.73423]},{"time":1.3333}]},"Layer14":{"Layer14":[{"curve":0.25,"c3":0.75},{"time":0.6667,"curve":0.25,"c3":0.75,"vertices":[13.18427,-8.63757,12.67963,18.58969,-31.71338,17.7682,-31.20874,-9.45906]},{"time":1.3333}]},"Layer15":{"Layer15":[{"curve":0.25,"c3":0.75},{"time":0.6667,"curve":0.25,"c3":0.75,"vertices":[-6.14142,-5.18671,-6.55927,9.02613,-11.36121,8.03522,-10.94336,-6.17758]},{"time":1.3333}]},"Layer22":{"Layer22":[{"curve":0.25,"c3":0.75},{"time":0.6667,"curve":0.25,"c3":0.75,"vertices":[-7.97272,17.4654,-5.56775,-18.28336,7.97272,-17.4654,5.56757,18.28337]},{"time":1.3333}]}}}},"quest2":{"slots":{"Layer11":{"attachment":[{"time":0.2,"name":null}]},"Layer12":{"attachment":[{"time":0.2,"name":null}]},"Layer13":{"attachment":[{"time":0.2,"name":null}]},"Layer14":{"attachment":[{"time":0.2,"name":null}]},"Layer15":{"attachment":[{"time":0.2,"name":null}]},"Layer16":{"attachment":[{"time":0.2,"name":"Layer16"}]},"Layer17":{"attachment":[{"time":0.2,"name":"Layer17"}]},"Layer18":{"attachment":[{"time":0.2,"name":"Layer18"}]},"Layer19":{"attachment":[{"time":0.2,"name":"Layer19"}]},"Layer20":{"attachment":[{"time":0.2,"name":"Layer20"}]},"Layer22":{"attachment":[{"time":0.2,"name":null}]},"Layer23":{"attachment":[{"time":0.1333,"name":"Layer24"}]}},"bones":{"Layer10":{"rotate":[{"angle":-0.98,"curve":0.25,"c3":0.75},{"time":0.3333,"angle":-4.86,"curve":0.25,"c3":0.625,"c4":0.5},{"time":0.5,"angle":-0.29}]},"Layer26":{"rotate":[{"angle":-4.09,"curve":0.25,"c3":0.75},{"time":0.5,"angle":-27.28}]},"Layer1":{"rotate":[{"angle":-8.14}]},"Layer8":{"rotate":[{"angle":1.42},{"time":0.5,"angle":9}],"scale":[{"curve":0.25,"c3":0.75},{"time":0.3333,"x":1.127}]},"Layer11":{"rotate":[{"angle":-2.51},{"time":0.5,"angle":-11.42}]},"Layer3":{"rotate":[{"angle":-0.51},{"time":0.5,"angle":8.54}],"scale":[{"curve":0.25,"c3":0.75},{"time":0.3333,"x":1.127}]},"Layer12":{"rotate":[{"angle":0.88},{"time":0.5,"angle":-15.54}]},"Layer6":{"rotate":[{"curve":0.25,"c3":0.75},{"time":0.2667,"angle":4.38,"curve":0.25,"c3":0.75},{"time":0.5,"angle":-4.35}]},"Layer28":{"rotate":[{"angle":-6.67,"curve":0.25,"c3":0.75},{"time":0.5,"angle":-29.86}]},"Layer23":{"rotate":[{"curve":0.25,"c3":0.75},{"time":0.2667,"angle":17.67,"curve":0.25,"c3":0.75},{"time":0.5,"angle":-1.59}]},"Layer2":{"rotate":[{"angle":-4.07}]},"Layer5":{"rotate":[{"curve":0.25,"c3":0.75},{"time":0.3333,"angle":-3.88}],"translate":[{"curve":0.25,"c3":0.75},{"time":0.3333,"y":35.14,"curve":0.25,"c3":0.625,"c4":0.5},{"time":0.5,"y":20.44}]},"Layer7":{"rotate":[{"angle":-0.36,"curve":0.25,"c3":0.75},{"time":0.3333,"angle":-4.24,"curve":0.25,"c3":0.625,"c4":0.5},{"time":0.5,"angle":0.33}]},"Layer30":{"rotate":[{"angle":-8.18,"curve":0.25,"c3":0.75},{"time":0.5,"angle":-31.37}]},"Layer4":{"rotate":[{"angle":-6.64}]}}}}},[0]]],0,0,[0],[-1],[0]]